LICENSE
setup.cfg
setup.py
jyotishyamitra.egg-info/PKG-INFO
jyotishyamitra.egg-info/SOURCES.txt
jyotishyamitra.egg-info/dependency_links.txt
jyotishyamitra.egg-info/top_level.txt
parashara/__init__.py
parashara/birthdata.py
parashara/dashas.py
parashara/mod_ashtakavarga.py
parashara/mod_astrodata.py
parashara/mod_bala.py
parashara/mod_constants.py
parashara/mod_divisional.py
parashara/mod_general.py
parashara/mod_json.py
parashara/mod_lagna.py
parashara/panchanga.py
parashara.egg-info/PKG-INFO
parashara.egg-info/SOURCES.txt
parashara.egg-info/dependency_links.txt
parashara.egg-info/top_level.txt