Metadata-Version: 2.1
Name: parashara
Version: 1.7
Summary: parashara
Home-page: https://github.com/digvijay2021/jyotishyamitra
Author: diggi
Author-email: diggi.gkp@gmail.com
Keywords: pip,jyotish
License-File: LICENSE
